skill_ovos_wallpapers/LICENSE
skill_ovos_wallpapers/MANIFEST.in
skill_ovos_wallpapers/README.md
skill_ovos_wallpapers/__init__.py
skill_ovos_wallpapers/settingsmeta.json
skill_ovos_wallpapers/version.py
skill_ovos_wallpapers/locale/ca-es/RandomKeyword.voc
skill_ovos_wallpapers/locale/ca-es/next.voc
skill_ovos_wallpapers/locale/ca-es/no.more.pictures.dialog
skill_ovos_wallpapers/locale/ca-es/picture.about.intent
skill_ovos_wallpapers/locale/ca-es/picture.random.intent
skill_ovos_wallpapers/locale/ca-es/previous.voc
skill_ovos_wallpapers/locale/ca-es/searching.dialog
skill_ovos_wallpapers/locale/ca-es/searching_random.dialog
skill_ovos_wallpapers/locale/ca-es/set.voc
skill_ovos_wallpapers/locale/ca-es/skill.json
skill_ovos_wallpapers/locale/ca-es/wallpaper.about.intent
skill_ovos_wallpapers/locale/ca-es/wallpaper.changed.dialog
skill_ovos_wallpapers/locale/ca-es/wallpaper.fail.dialog
skill_ovos_wallpapers/locale/ca-es/wallpaper.random.intent
skill_ovos_wallpapers/locale/ca-es/wallpapers.voc
skill_ovos_wallpapers/locale/da-dk/RandomKeyword.voc
skill_ovos_wallpapers/locale/da-dk/next.voc
skill_ovos_wallpapers/locale/da-dk/no.more.pictures.dialog
skill_ovos_wallpapers/locale/da-dk/picture.about.intent
skill_ovos_wallpapers/locale/da-dk/picture.random.intent
skill_ovos_wallpapers/locale/da-dk/previous.voc
skill_ovos_wallpapers/locale/da-dk/searching.dialog
skill_ovos_wallpapers/locale/da-dk/searching_random.dialog
skill_ovos_wallpapers/locale/da-dk/set.voc
skill_ovos_wallpapers/locale/da-dk/skill.json
skill_ovos_wallpapers/locale/da-dk/wallpaper.about.intent
skill_ovos_wallpapers/locale/da-dk/wallpaper.changed.dialog
skill_ovos_wallpapers/locale/da-dk/wallpaper.fail.dialog
skill_ovos_wallpapers/locale/da-dk/wallpaper.random.intent
skill_ovos_wallpapers/locale/da-dk/wallpapers.voc
skill_ovos_wallpapers/locale/de-de/AVPorn.voc
skill_ovos_wallpapers/locale/de-de/AbandonedPorn.voc
skill_ovos_wallpapers/locale/de-de/AdPorn.voc
skill_ovos_wallpapers/ovos_skill_wallpapers.egg-info/PKG-INFO
skill_ovos_wallpapers/ovos_skill_wallpapers.egg-info/SOURCES.txt
skill_ovos_wallpapers/ovos_skill_wallpapers.egg-info/dependency_links.txt
skill_ovos_wallpapers/ovos_skill_wallpapers.egg-info/entry_points.txt
skill_ovos_wallpapers/ovos_skill_wallpapers.egg-info/top_level.txt
ovos_skill_wallpapers-1.0.9.dist-info/LICENSE
ovos_skill_wallpapers-1.0.9.dist-info/METADATA
ovos_skill_wallpapers-1.0.9.dist-info/WHEEL
ovos_skill_wallpapers-1.0.9.dist-info/entry_points.txt
ovos_skill_wallpapers-1.0.9.dist-info/top_level.txt
ovos_skill_wallpapers-1.0.9.dist-info/RECORD
