Metadata-Version: 2.1
Name: ovos-skill-wallpapers
Version: 1.0.9
Summary: OVOS wallpapers skill
Home-page: https://github.com/OpenVoiceOS/skill-ovos-wallpapers
Author: OpenVoiceOS
Author-email: jarbasai@mailfence.com
License: Apache-2.0
Keywords: ovos skill plugin
Platform: UNKNOWN
